lost_cat_images/__init__.py
lost_cat_images/examples/init_lostcat.py
lost_cat_images/examples/run_engimg.py
lost_cat_images/examples/run_v2.py
lost_cat_images/examples/save_rules.py
lost_cat_images/parsers/__init__.py
lost_cat_images/parsers/engimg_parser.py
lost_cat_images/parsers/image_parser.py
lost_cat_images/parsers/pdf_parser.py
lost_cat_images/processors/__init__.py
lost_cat_images/processors/image_processor.py
lost_cat_images/utils/__init__.py
lost_cat_images/utils/clean.py
lost_cat_images/utils/extract.py
lost_cat_images/utils/image_templates.py
lost_cat_images/utils/tools.py
lost_cat_images/utils/utils_boxes.py
lost_cat_images/utils/utils_graphics.py
lost_cat_images/utils/utils_grids.py
lost_cat_images/utils/utils_image.py
lost_cat_images/utils/utils_nodepaths.py
lost_cat_images/utils/utils_ocr.py
lost_cat_images/utils/utils_ocr_engines.py
lost_cat_images/utils/utils_pdf.py
lost_cat_images/utils/utils_rules.py
lost_cat_images/utils/utils_shapes.py
lost_cat_images/utils/utils_text.py
lost_cat_images/utils/utils_words.py
lost_cat_images-1.1.0.dist-info/LICENSE
lost_cat_images-1.1.0.dist-info/METADATA
lost_cat_images-1.1.0.dist-info/WHEEL
lost_cat_images-1.1.0.dist-info/top_level.txt
lost_cat_images-1.1.0.dist-info/RECORD
