Metadata-Version: 2.1
Name: lost-cat-images
Version: 1.1.0
Summary: Lost Cat (images) is a package for image related uris and tools
Author-email: Dreffed aka David Gloyn-Cox <dreffed@gmail.com>, Thoughtswin Systems Inc <david.gloyn-cox@thoughtswinsystems.com>
License: MIT License
Project-URL: Homepage, https://github.com/thoughtswinsystems/lost_cat_images
Project-URL: Bug Tracker, https://github.com/thoughtswinsystems/lost_cat_images/issues
Classifier: Programming Language :: Python :: 3
Classifier: License :: OSI Approved :: MIT License
Classifier: Operating System :: OS Independent
Requires-Python: >=3.8
License-File: LICENSE
Requires-Dist: lost-cat >=0.1.6
Requires-Dist: lost-cat-office
Requires-Dist: numpy
Requires-Dist: opencv-python
Requires-Dist: pandas
Requires-Dist: pillow
Requires-Dist: psutil
Requires-Dist: pymupdf
Requires-Dist: pytesseract
Requires-Dist: python-dotenv
Requires-Dist: scipy
Requires-Dist: scikit-image
Requires-Dist: xlsxwriter
Requires-Dist: openpyxl
